README.rst
setup.py
destructify/__init__.py
destructify/exceptions.py
destructify.egg-info/PKG-INFO
destructify.egg-info/SOURCES.txt
destructify.egg-info/dependency_links.txt
destructify.egg-info/requires.txt
destructify.egg-info/top_level.txt
destructify/fields/__init__.py
destructify/fields/base.py
destructify/fields/common.py
destructify/fields/struct.py
destructify/fields/wrapped.py
destructify/gui/__init__.py
destructify/gui/__main__.py
destructify/gui/tk.py
destructify/parsing/__init__.py
destructify/parsing/bitstream.py
destructify/parsing/context.py
destructify/parsing/expression.py
destructify/parsing/substream.py
destructify/structures/__init__.py
destructify/structures/base.py
destructify/structures/options.py