Metadata-Version: 1.1
Name: destructify
Version: 0.2.0
Summary: A Pythonic way to define, parse and modify binary structures
Home-page: https://github.com/ralphje/destructify
Author: Ralph Broenink
Author-email: ralph@ralphbroenink.net
License: MIT
Download-URL: https://github.com/ralphje/destructify/tarball/v0.2.0
Keywords: struct,bytes
Platform: UNKNOWN
Classifier: Development Status :: 2 - Pre-Alpha
Classifier: Intended Audience :: Developers
Classifier: License :: OSI Approved :: MIT License
Classifier: Programming Language :: Python :: 3.5
Classifier: Programming Language :: Python :: 3.6
Classifier: Programming Language :: Python :: 3.7
Classifier: Topic :: Software Development :: Libraries :: Python Modules
